QBsimpleAPI/QBsimpleAPI.py
QBsimpleAPI/__init__.py
QBsimpleAPI-0.0.2.dist-info/LICENSE
QBsimpleAPI-0.0.2.dist-info/METADATA
QBsimpleAPI-0.0.2.dist-info/WHEEL
QBsimpleAPI-0.0.2.dist-info/top_level.txt
QBsimpleAPI-0.0.2.dist-info/RECORD
